AUTHORS.md
LICENSE
MANIFEST.in
README.md
setup.cfg
setup.py
django_grpc_secure/__init__.py
django_grpc_secure/__version__.py
django_grpc_secure/apps.py
django_grpc_secure/models.py
django_grpc_secure/utils.py
django_grpc_secure.egg-info/PKG-INFO
django_grpc_secure.egg-info/SOURCES.txt
django_grpc_secure.egg-info/dependency_links.txt
django_grpc_secure.egg-info/not-zip-safe
django_grpc_secure.egg-info/requires.txt
django_grpc_secure.egg-info/top_level.txt
django_grpc_secure/management/__init__.py
django_grpc_secure/management/commands/grpcserversecure.py
django_grpc_secure/serializers/__init__.py
django_grpc_secure/serializers/base.py
django_grpc_secure/signals/__init__.py
django_grpc_secure/signals/wrapper.py
django_grpc_testtools/__init__.py
django_grpc_testtools/context.py
django_grpc_testtools/executor.py