Metadata-Version: 2.1
Name: django-grpc-secure
Version: 0.1.0
Summary: Easy Django based gRPC service with secure
Home-page: UNKNOWN
Author: Qibin Jin
Author-email: qibin9112@gmail.com
License: MIT
Keywords: django-grpc-secure
Platform: UNKNOWN
Classifier: Development Status :: 5 - Production/Stable
Classifier: Intended Audience :: Developers
Classifier: License :: OSI Approved :: MIT License
Classifier: Natural Language :: English
Classifier: Programming Language :: Python :: 3
Classifier: Programming Language :: Python :: 3.4
Classifier: Programming Language :: Python :: 3.5
Classifier: Programming Language :: Python :: 3.6
Classifier: Programming Language :: Python :: 3.7
